react_ssr/__init__.py
react_ssr/exceptions.py
react_ssr/mixins.py
react_ssr/render.py
react_ssr/settings.py
react_ssr/utils.py
react_ssr/views.py
react_ssr/mixins/__init__.py
react_ssr/mixins/auth_state.py
react_ssr/mixins/authentication_state.py
react_ssr/mixins/core_state.py
react_ssr/mixins/default_state.py
react_ssr/mixins/included_states.py
react_ssr/mixins/page_state.py
react_ssr/mixins/render.py
react_ssr/mixins/secret_key.py
react_ssr/mixins/set_state.py
react_ssr/mixins/user_agent.py
react_ssr/mixins/base/__init__.py
react_ssr/mixins/base/default_state.py
react_ssr/mixins/base/included_states.py
react_ssr/mixins/base/page_state.py
react_ssr/mixins/base/render.py
react_ssr/mixins/base/set_state.py
react_ssr/settings/__init__.py
react_ssr/settings/auth_state.py
react_ssr/settings/authentication_state.py
react_ssr/settings/core_state.py
react_ssr/settings/default_state.py
react_ssr/settings/render.py
react_ssr/settings/secret_key.py
react_ssr/settings/user_agent.py
react_ssr/templates/react_ssr/base.html
react_ssr-5.0.0.dist-info/LICENSE.txt
react_ssr-5.0.0.dist-info/METADATA
react_ssr-5.0.0.dist-info/WHEEL
react_ssr-5.0.0.dist-info/top_level.txt
react_ssr-5.0.0.dist-info/RECORD
