Metadata-Version: 2.1
Name: react-ssr
Version: 5.0.0
Summary: UNKNOWN
Home-page: https://github.com/alexseitsinger/react-ssr-backend
Author: Alex Seitsinger
Author-email: software@alexseitsinger.com
License: BSD 2-Clause License
Project-URL: Documentation, https://github.com/alexseitsinger/react-ssr-backend
Project-URL: Source, https://github.com/alexseitsinger/react-ssr-backend
Project-URL: Tracker, https://github.com/alexseitsinger/react-ssr-backend/issues
Keywords: django,react,server-side rendering
Platform: UNKNOWN
Classifier: License :: OSI Approved :: BSD License
Classifier: Programming Language :: Python :: 2
Classifier: Programming Language :: Python :: 3
Classifier: Environment :: Console
Classifier: Environment :: Web Environment
Classifier: Intended Audience :: Developers
Classifier: Topic :: Software Development
Classifier: Topic :: Internet :: WWW/HTTP :: HTTP Servers
Classifier: Topic :: Internet :: WWW/HTTP :: Browsers
Classifier: Framework :: Django
Classifier: Natural Language :: English
Classifier: Operating System :: OS Independent
Requires-Dist: requests
Requires-Dist: Django (>=1.11)
Requires-Dist: click
